LICENSE
README.md
setup.py
optimtool/__init__.py
optimtool/_convert.py
optimtool/_drive.py
optimtool/_kernel.py
optimtool/_proxim.py
optimtool/_search.py
optimtool/_typing.py
optimtool/_utils.py
optimtool/_version.py
optimtool/base.py
optimtool.egg-info/PKG-INFO
optimtool.egg-info/SOURCES.txt
optimtool.egg-info/dependency_links.txt
optimtool.egg-info/not-zip-safe
optimtool.egg-info/requires.txt
optimtool.egg-info/top_level.txt
optimtool/constrain/__init__.py
optimtool/constrain/equal.py
optimtool/constrain/mixequal.py
optimtool/constrain/unequal.py
optimtool/example/Lasso.py
optimtool/example/WanYuan.py
optimtool/example/__init__.py
optimtool/hybrid/__init__.py
optimtool/hybrid/approt.py
optimtool/hybrid/fista.py
optimtool/hybrid/nesterov.py
optimtool/unconstrain/__init__.py
optimtool/unconstrain/gradient_descent.py
optimtool/unconstrain/newton.py
optimtool/unconstrain/newton_quasi.py
optimtool/unconstrain/nonlinear_least_square.py
optimtool/unconstrain/trust_region.py