Metadata-Version: 2.1
Name: optimtool
Version: 2.5.1
Summary: The fundamental package for scientific research in optimization.
Home-page: https://github.com/linjing-lab/optimtool
Download-URL: https://github.com/linjing-lab/optimtool/tags
Author: 林景
Author-email: linjing010729@163.com
License: MIT
Project-URL: Source, https://github.com/linjing-lab/optimtool/tree/master/optimtool/
Project-URL: Tracker, https://github.com/linjing-lab/optimtool/issues
Classifier: Development Status :: 5 - Production/Stable
Classifier: Intended Audience :: Developers
Classifier: Intended Audience :: Education
Classifier: Intended Audience :: Science/Research
Classifier: Programming Language :: Python :: 3.7
Classifier: Programming Language :: Python :: 3.8
Classifier: Programming Language :: Python :: 3.9
Classifier: Programming Language :: Python :: 3.10
Classifier: Programming Language :: Python :: 3.11
Classifier: License :: OSI Approved :: MIT License
Classifier: Topic :: Scientific/Engineering
Classifier: Topic :: Scientific/Engineering :: Mathematics
Classifier: Topic :: Software Development
Classifier: Topic :: Software Development :: Libraries
Classifier: Topic :: Software Development :: Libraries :: Python Modules
License-File: LICENSE
